Metadata-Version: 1.0
Name: steem-watchdog
Version: 0.0.1
Summary: Automates claiming process of author/curation rewards
Home-page: http://github.com/emre/steem-watchdog
Author: Emre Yilmaz
Author-email: mail@emreyilmaz.me
License: MIT
Platform: UNKNOWN
